{"title": "Local Weather Radar & Forecast", "icon": "https://lh3.googleusercontent.com/PLIz3Krm05ZQbutiDt9J2_PIeMp5kglay6Ft79O5hLSiEOsAq4pjch978U5SP2hdvhB-", "screenshots": ["https://lh3.googleusercontent.com/w_uOev6AyRC4zyWnyKQFFsFoD0gp3BahjxGPQml7SsqSjuUVz85989EH4vFeybV60wA=w720-h310-rw", "https://lh3.googleusercontent.com/0LnaBqdsyoVa3veEYVlo_So8u0DEuhL5Ej-04OFbKW2xIOWhIZSyeJ4cI3sbZiUChGZM=w720-h310-rw", "https://lh3.googleusercontent.com/xIYa7baYqc9XeHyxYX2-iXE96eq27rOyZjWtPzwvp3TZYMIqGtWXU6qlVIboEDp8GQk=w720-h310-rw", "https://lh3.googleusercontent.com/JhAV6RaZNtowRIqEYjteW4CYWFny6Ma5OlMk3xlOjR6FZX3a8xdYoUKWinKecNV1ooI=w720-h310-rw", "https://lh3.googleusercontent.com/n5yXXq5Ec9TGb11Uvc2LXZ_1iqvOeIaETG2PRYrNqIYH8KN1gZ8a2XnBS6r8FfLaC1M=w720-h310-rw"], "video": null, "category": ["WEATHER"], "score": "4.4", "histogram": {"5": null, "4": null, "3": null, "2": null, "1": null}, "reviews": 3889, "description": "Local Weather is the one app for local breaking weather news & traffic for the world & USA.\nThe free Local Weather app includes:\n> Local forecast, conditions, with satellite maps & doppler radar trackers\n> Hourly temperature timeline to plan your day\n> Hurricane & typhoon forecasts from the NOAA\n> Live traffic and emergency transit alert updates\n> Current moon phase and sun location widget\n> Daily weather history.\n> Plus, express weather news notifications for multiple geographic locations.\n> It's a weather station in your hand!\nDownload Local Weather app now for free & keep an eye on your source for weather.", "description_html": "Local Weather is the one app for local breaking weather news &amp; traffic for the world &amp; USA.<br/><br/>The free Local Weather app includes:<br/>&gt; Local forecast, conditions, with satellite maps &amp; doppler radar trackers<br/>&gt; Hourly temperature timeline to plan your day<br/>&gt; Hurricane &amp; typhoon forecasts from the NOAA<br/>&gt; Live traffic and emergency transit alert updates<br/>&gt; Current moon phase and sun location widget<br/>&gt; Daily weather history.<br/>&gt; Plus, express weather news notifications for multiple geographic locations.<br/>&gt; It's a weather station in your hand!<br/><br/>Download Local Weather app now for free &amp; keep an eye on your source for weather.", "recent_changes": null, "editors_choice": false, "price": "0", "free": true, "iap": false, "developer_id": "Mediasota+News+Apps", "updated": "October 16, 2019", "size": "20M", "installs": "500,000+", "current_version": "v4.34.0.2", "required_android_version": "5.0 and up", "content_rating": ["Everyone"], "iap_range": null, "interactive_elements": null, "developer": "Mediasota News Apps", "developer_email": "android@doapps.com", "developer_url": "http://www.doapps.com", "developer_address": null, "app_id": "com.doapps.android.mln.MLN_8e6313c7f610ef1e4e1e7baca2878b8e", "url": "https://play.google.com/store/apps/details?id=com.doapps.android.mln.MLN_8e6313c7f610ef1e4e1e7baca2878b8e"}