{"title": "SATCH VIEWER", "icon": "https://lh3.googleusercontent.com/IDHQwM6w6M1jN4d6vz1EHnDM8kAi7p0HxwuMCU3kZo4Qj3lP5mDUUwl7aeTsFhgA-A", "screenshots": ["https://lh3.googleusercontent.com/gEUZY77Ai96apfCsEKqQzbtyMacbCIQI6tmeT6rgNdx7MqXdobizgkv4j20RdxJNIQ3S=w720-h310-rw", "https://lh3.googleusercontent.com/VBEzkpA0L8RaiWGwB430vh2VsJzwysn3N5QJnIsbx8WJZA4yVmOqnRve2B8Eb9NrNg=w720-h310-rw", "https://lh3.googleusercontent.com/Q4mqmRAjQ95EkZSqzxn_cWOy8m0iQgyeVsrfYczEmfXZnM7YFFLEg-KT1MO2F0aHmUc=w720-h310-rw"], "video": null, "category": ["ENTERTAINMENT"], "score": "2.9", "histogram": {"5": null, "4": null, "3": null, "2": null, "1": null}, "reviews": 1595, "description": "\u65b0\u30b3\u30f3\u30c6\u30f3\u30c4\u6e80\u8f09\u306eSATCH VIEWER!!\n\u3010\u4f7f\u3044\u65b9\u3011\n1)\u30a2\u30d7\u30ea\u3092\u8d77\u52d5\u3057\u3066\u300c\u3044\u307e\u3059\u3050SCAN!\u300d\u3092\u9078\u629e\n2)\u30ab\u30e1\u30e9\u304c\u8d77\u52d5\u3057\u305f\u3089\u3001\u8a8d\u8b58\u5bfe\u8c61\u3068\u306a\u308b\u3082\u306e\u3092\u304b\u3056\u3057\u3066\u30bf\u30c3\u30d7\uff01\n3)\u4e0a\u624b\u304f\u8a8d\u8b58\u3057\u305f\u3089\u3001\u305d\u306e\u5bfe\u8c61\u306b\u7d10\u3065\u3044\u305f\u30b3\u30f3\u30c6\u30f3\u30c4\u304c\u51fa\u73fe\u3057\u307e\u3059\u3002", "description_html": "\u65b0\u30b3\u30f3\u30c6\u30f3\u30c4\u6e80\u8f09\u306eSATCH VIEWER!!<br/><br/> <br/>\u3010\u4f7f\u3044\u65b9\u3011<br/> \u30001)\u30a2\u30d7\u30ea\u3092\u8d77\u52d5\u3057\u3066\u300c\u3044\u307e\u3059\u3050SCAN!\u300d\u3092\u9078\u629e<br/> \u30002)\u30ab\u30e1\u30e9\u304c\u8d77\u52d5\u3057\u305f\u3089\u3001\u8a8d\u8b58\u5bfe\u8c61\u3068\u306a\u308b\u3082\u306e\u3092\u304b\u3056\u3057\u3066\u30bf\u30c3\u30d7\uff01<br/> \u30003)\u4e0a\u624b\u304f\u8a8d\u8b58\u3057\u305f\u3089\u3001\u305d\u306e\u5bfe\u8c61\u306b\u7d10\u3065\u3044\u305f\u30b3\u30f3\u30c6\u30f3\u30c4\u304c\u51fa\u73fe\u3057\u307e\u3059\u3002", "recent_changes": null, "editors_choice": false, "price": "0", "free": true, "iap": false, "developer_id": "KDDI%E6%A0%AA%E5%BC%8F%E4%BC%9A%E7%A4%BE", "updated": "July 15, 2020", "size": "155M", "installs": "5,000,000+", "current_version": "7.2.5", "required_android_version": "4.1 and up", "content_rating": ["Everyone"], "iap_range": null, "interactive_elements": null, "developer": "KDDI\u682a\u5f0f\u4f1a\u793e", "developer_email": "satch-support@kddi.com", "developer_url": "http://viewer.satch.jp", "developer_address": null, "app_id": "com.kddi.ar.satch.satchviewer", "url": "https://play.google.com/store/apps/details?id=com.kddi.ar.satch.satchviewer"}