{"title": "Calm - Meditate, Sleep, Relax", "icon": "https://lh3.googleusercontent.com/S76GphUu2pZa249td2Bb4XAhLcPRrFdL1zp_5qU1ouukvRq9r0-8jJ-CruaTtdT6g84", "screenshots": ["https://lh3.googleusercontent.com/LPSOSstV--uFRxwNI6K4HWr9pWnh-Ufe3IVEDeJXDcMGBTODCcu3QD94lAyzqgjd9k4=w720-h310-rw", "https://lh3.googleusercontent.com/z8vVoYZvcjYWkxRwSSae_TK1QOyEbt8KEWTD2KUlB5u7gYOjoMUPVs64l5uP6tFdlvk=w720-h310-rw", "https://lh3.googleusercontent.com/nuWp8yQCVyGzm6FDcsdK9CDfF6wt09_y0eFK4f39sPgSI6qkaF3WsUDcgQSiOWHCHKK-=w720-h310-rw", "https://lh3.googleusercontent.com/g8ThAN9o1_q3bhS2beO9fimmMBTO_MzJnf24adteHnGdnBQmDncqEeEN9WVoopAxv5Qm=w720-h310-rw", "https://lh3.googleusercontent.com/77WYs593sEChGcNtMbNqRDpyAopxUa_1D04gzEMvmcOophSPS9yvDkqD0vl66SJxcA=w720-h310-rw", "https://lh3.googleusercontent.com/_jRoaPUvL3E_rtw7WXChG8wrRywPQa1ZH9dZiPgqhiaNE_4NXKvwgRr6Fl37udqDzw=w720-h310-rw"], "video": null, "category": ["HEALTH_AND_FITNESS"], "score": "4.4", "histogram": {"5": null, "4": null, "3": null, "2": null, "1": null}, "reviews": 278707, "description": "Calm is a leading app for meditation and sleep. Join the millions experiencing lower stress, less anxiety, and more restful sleep with our guided meditations, Sleep Stories, breathing programs, masterclasses, and relaxing music. Recommended by top psychologists, therapists, and mental health experts.\nCalm is the perfect mindfulness app for beginners, but also includes hundreds of programs for intermediate and advanced users.\nGuided meditation sessions are available in lengths of 3, 5, 10, 15, 20 or 25 minutes so you can choose the perfect length to fit with your schedule. Topics include:\n* Calming Anxiety\n* Managing Stress\n* Deep Sleep\n* Focus and Concentration\n* Relationships\n* Breaking Habits\n* Happiness\n* Gratitude\n* Self-Esteem\n* Body Scan\n* Loving-Kindness\n* Forgiveness\n* Non-judgement\n* Commuting to work or school\n* Mindfulness at College\n* Mindfulness at Work\n* Walking meditation\n* Calm Kids\n* And so much more...\nAlso featuring:\n* An original Daily Calm every day: a new 10-minute program added daily to help ease you into the day or unwind with before bed\n* 100+ Sleep Stories: adult bedtime stories guaranteed to lull you to sleep\n* 7 and 21 day programs for both beginner and advanced users\n* Life-changing Calm Masterclasses taught by world-renowned experts\n* Breathing exercises to help you relax\n* Exclusive music engineered to help you focus, relax or sleep\n* Unguided timed meditation\n* Open-ended meditation\n* 30+ soothing nature sounds and scenes to use during meditation, yoga or to help you sleep\nTrack your progress with:\n* Daily streaks\n* Time spent meditating\nCalm is loved by the press:\n* \u201cI\u2019m generally wary of meditation apps because they sometimes weave in too much mystic talk for my taste. But Calm instead contains guidance like \u2018Concentrate on your body\u2019\u201d - New York Times\n* \u201cIn the frenetic, crazy, digital world we live in, sometimes it's necessary to take a step back and smell the roses\u201d - Mashable\n* \u201cEliminating distraction...ended up helping me relax and realize that all the stuff I was stressing about wasn't that big a deal\u201d - Tech Republic\n* \u201cFound myself similarly refreshed afterwards\u201d - TechCrunch\nCalm is free to download and use, and there are no ads. A subset of the programs and features are free forever.\nSome content is only available through an optional paid subscription. If you choose to subscribe, payment will be charged to your Google Account at confirmation of purchase.", "description_html": "Calm is a leading app for meditation and sleep. Join the millions experiencing lower stress, less anxiety, and more restful sleep with our guided meditations, Sleep Stories, breathing programs, masterclasses, and relaxing music. Recommended by top psychologists, therapists, and mental health experts.<br/><br/>Calm is the perfect mindfulness app for beginners, but also includes hundreds of programs for intermediate and advanced users.<br/><br/>Guided meditation sessions are available in lengths of 3, 5, 10, 15, 20 or 25 minutes so you can choose the perfect length to fit with your schedule. Topics include:<br/><br/>* Calming Anxiety<br/>* Managing Stress<br/>* Deep Sleep<br/>* Focus and Concentration<br/>* Relationships<br/>* Breaking Habits<br/>* Happiness<br/>* Gratitude<br/>* Self-Esteem<br/>* Body Scan<br/>* Loving-Kindness<br/>* Forgiveness<br/>* Non-judgement<br/>* Commuting to work or school<br/>* Mindfulness at College<br/>* Mindfulness at Work<br/>* Walking meditation<br/>* Calm Kids<br/>* And so much more...<br/><br/>Also featuring:<br/><br/>* An original Daily Calm every day: a new 10-minute program added daily to help ease you into the day or unwind with before bed<br/>* 100+ Sleep Stories: adult bedtime stories guaranteed to lull you to sleep<br/>* 7 and 21 day programs for both beginner and advanced users<br/>* Life-changing Calm Masterclasses taught by world-renowned experts<br/>* Breathing exercises to help you relax<br/>* Exclusive music engineered to help you focus, relax or sleep<br/>* Unguided timed meditation<br/>* Open-ended meditation<br/>* 30+ soothing nature sounds and scenes to use during meditation, yoga or to help you sleep<br/><br/>Track your progress with:<br/><br/>* Daily streaks<br/>* Time spent meditating<br/><br/>Calm is loved by the press:<br/><br/>* \u201cI\u2019m generally wary of meditation apps because they sometimes weave in too much mystic talk for my taste. But Calm instead contains guidance like \u2018Concentrate on your body\u2019\u201d - New York Times<br/><br/>* \u201cIn the frenetic, crazy, digital world we live in, sometimes it's necessary to take a step back and smell the roses\u201d - Mashable<br/><br/>* \u201cEliminating distraction...ended up helping me relax and realize that all the stuff I was stressing about wasn't that big a deal\u201d - Tech Republic<br/><br/>* \u201cFound myself similarly refreshed afterwards\u201d - TechCrunch<br/><br/>Calm is free to download and use, and there are no ads. A subset of the programs and features are free forever.<br/><br/>Some content is only available through an optional paid subscription. If you choose to subscribe, payment will be charged to your Google Account at confirmation of purchase.", "recent_changes": null, "editors_choice": true, "price": "0", "free": true, "iap": true, "developer_id": "Calm.com,+Inc.", "updated": "July 23, 2020", "size": "Varies with device", "installs": "10,000,000+", "current_version": "Varies with device", "required_android_version": "Varies with device", "content_rating": ["Everyone"], "iap_range": ["$0.99", "$399.99"], "interactive_elements": ["Digital Purchases"], "developer": "Calm.com, Inc.", "developer_email": "android@calm.com", "developer_url": "http://www.calm.com", "developer_address": "140 2nd Street\n3rd Floor\nSan Francisco\nCA 94105", "app_id": "com.calm.android", "url": "https://play.google.com/store/apps/details?id=com.calm.android"}