{"title": "7shifts: Employee Scheduling", "icon": "https://lh3.googleusercontent.com/ZbZLjpPL1x2XBHjkk5AuuBrjL4dCbSVX65_6IcfF2i7xo3oBGcPb9HhfRJ4JD1Tquvg", "screenshots": ["https://lh3.googleusercontent.com/N90m0bhUELmyZwRCsd-w7d4bdp0l2GqI2zi80ZCIhGEXb7nxTFMLUwmCehmbVgSJHWM=w720-h310-rw", "https://lh3.googleusercontent.com/JTJcWDjP3YLz5tauNkp_U2oPxUItViZSrker1WD7QzAQGvaGWpruSaybgUWzk0zvhg=w720-h310-rw", "https://lh3.googleusercontent.com/z8rwZ5dT_M1OBrY5Fg-Q5ZS-ef06bGwu2FF1M-v7wkX1fpwtot7q1RCL9GmFa_2voSY=w720-h310-rw", "https://lh3.googleusercontent.com/UN2zsrML2whGakmIXsbOGwzvPFxtaEj7T2qa6AjRMZ1swe62pKO_jhYoswteOtBq138=w720-h310-rw", "https://lh3.googleusercontent.com/9cul5-NlBxkrRaqtRMR2fFuQ1pxpJXNO4Q5fkw7o17EWFUN9XAiF2_DViCp8WLKbmQ=w720-h310-rw", "https://lh3.googleusercontent.com/YjxiyzodF4egNTHCOKXms5Z58RYoq13419lWAK4ljbjaKjhHOR0t78Jg_z_IcZujfoE=w720-h310-rw", "https://lh3.googleusercontent.com/xRTtCEj4EerudjpJdHrGXziZq6csXlbe5G1VmRLEEiRlnw1jdgwH-d9_RRjYSvJWFBk=w720-h310-rw", "https://lh3.googleusercontent.com/e-ogPGeMmsoAYWm0GVZieW42S_9K9CxCaHvaZWFG9XA9o5mamwVcilFJSsLen4hmUng8=w720-h310-rw", "https://lh3.googleusercontent.com/Vi06j4KgGabkJoVMJRg87QxWvYPTIYo8SvO_h7Ffisxoxi2z-WwgktrzFT-k5VybyHE=w720-h310-rw", "https://lh3.googleusercontent.com/5009CMVUaj9lIlRTHiOEnbQkseHdyFa138iO6dnVUdatHQho9RYIYN2slNeLXWqJ2I8=w720-h310-rw", "https://lh3.googleusercontent.com/ZZkWDhbZ5uMipTv5QgN1s66zwHKswWlJbr7-jl5Ec7ohdNAfZsWWX-9dBliwRqqrr_s=w720-h310-rw", "https://lh3.googleusercontent.com/lMY2PSjTjdIQULBsI1cQioAkcePs_RBw2-BZJkK8Aqk3ZXxWLV5t4uxog8A8Mui9oyw=w720-h310-rw", "https://lh3.googleusercontent.com/kMaqhyJ_NbSCKEVopYNBA46x5kISOXM0u9sd9M2EOFboCyTkgDgALOpMz50TjjHOhGlt=w720-h310-rw"], "video": "https://www.youtube.com/embed/JEOSjY9pN7k", "category": ["BUSINESS"], "score": "4.6", "histogram": {"5": null, "4": null, "3": null, "2": null, "1": null}, "reviews": 1943, "description": "The 7shifts restaurant scheduling app makes it easy to manage schedules and communicate with staff on the go.\nWith 7shifts, your managers can edit work schedules, communicate with and engage staff, track real-time sales and labor data, and stay labor compliant. The employee app empowers your team to take availability and time-off requests, shift trading, and communication into their own hands\u2014anytime, anywhere.\nThe 7shifts app is free for all restaurant employees to use as part of your 7shifts subscription.\nFeatures for restaurant managers:\n- Manage the schedule with time-off and availability automatically added\n- Notify staff of their shifts automatically via email, text, or push notification\n- Approve or deny shift trades\n- Approve or deny time-off requests\n- Track staff availability\n- Track staff engagement like lates and no-shows\n- Chat with staff or create team-wide announcements\n- Get overtime alerts if staff are at risk of going into overtime\n- Track real-time sales and labor to make smart decisions to reduce labor cost\nFeatures for restaurant employees:\n- View all of your shifts\n- See who you are working with for upcoming shifts\n- View hours and estimated earnings\n- Request shift trades\n- Request time off\n- Submit your availability\n- Chat with GIFs, pics, or emojis with your co-workers\nThe 7shifts team is focused on making employee scheduling easier for managers in the restaurant industry, and make employees happier in the workplace. See how easy life is with 7shifts.", "description_html": "The 7shifts restaurant scheduling app makes it easy to manage schedules and communicate with staff on the go. <br/><br/>With 7shifts, your managers can edit work schedules, communicate with and engage staff, track real-time sales and labor data, and stay labor compliant. The employee app empowers your team to take availability and time-off requests, shift trading, and communication into their own hands\u2014anytime, anywhere. <br/><br/>The 7shifts app is free for all restaurant employees to use as part of your 7shifts subscription.<br/><br/>Features for restaurant managers:<br/>    - Manage the schedule with time-off and availability automatically added<br/>    - Notify staff of their shifts automatically via email, text, or push notification<br/>    - Approve or deny shift trades<br/>    - Approve or deny time-off requests<br/>    - Track staff availability<br/>    - Track staff engagement like lates and no-shows<br/>    - Chat with staff or create team-wide announcements<br/>    - Get overtime alerts if staff are at risk of going into overtime<br/>    - Track real-time sales and labor to make smart decisions to reduce labor cost<br/><br/>Features for restaurant employees:<br/>    - View all of your shifts<br/>    - See who you are working with for upcoming shifts<br/>    - View hours and estimated earnings<br/>    - Request shift trades<br/>    - Request time off<br/>    - Submit your availability<br/>    - Chat with GIFs, pics, or emojis with your co-workers<br/><br/>The 7shifts team is focused on making employee scheduling easier for managers in the restaurant industry, and make employees happier in the workplace. See how easy life is with 7shifts.", "recent_changes": null, "editors_choice": false, "price": "0", "free": true, "iap": false, "developer_id": "7shifts,+Inc.", "updated": "August 4, 2020", "size": "31M", "installs": "100,000+", "current_version": "2020.29.2", "required_android_version": "5.0 and up", "content_rating": ["Everyone"], "iap_range": null, "interactive_elements": ["Users Interact"], "developer": "7shifts, Inc.", "developer_email": "info@7shifts.com", "developer_url": "http://www.7shifts.com", "developer_address": "200 - 701 Broadway Avenue\nSaskatoon, SK\nS7N 1B3", "app_id": "com.sevenshifts.android", "url": "https://play.google.com/store/apps/details?id=com.sevenshifts.android"}