{"title": "Delta Community Credit Union", "icon": "https://lh3.googleusercontent.com/9OIxmsThe3aackZ9yyI1LWbheXq3wHSBFt5dE7NWrC24ajdvuuPyQCLpYyrRzs_xa5xd", "screenshots": ["https://lh3.googleusercontent.com/GcOxiVMMOzzBvsTdzZzh-19TTNc2iZRJ8YowRRODQ0IqTggXI2HH3ueCc8wS5DDq-Qg5=w720-h310-rw", "https://lh3.googleusercontent.com/SEHuBaCL5t8ngh6xZm40fJomOHmuiBH_tYAZXZxaUD49hl9jr4k627WleMaKSE5xmlI=w720-h310-rw", "https://lh3.googleusercontent.com/iTRDAqrrHA8ow94TufphgCe3rpALTDcBVkuQGZA99ahIK2aDdPFbr9p_nuEgRUlN9TY=w720-h310-rw", "https://lh3.googleusercontent.com/cDU_UjUMR7xNK3S_Xwc1pr3RNcot8SLwY7RWyUScoY5pGCAl46AWH6IBvLOryeS3EA=w720-h310-rw", "https://lh3.googleusercontent.com/wJSx4v9LooZADcCFyILHnsWl1Zjoo5JRMvoobYrpGJ09kexkHOmyrYVeQVP5MPdsqDzd=w720-h310-rw", "https://lh3.googleusercontent.com/kyFhbo7HK41Iv4qXVtHgQ8XiQd8tIuS67z2SQQDp04JOqn4NOibDMW_uc3bCf4bo4L38=w720-h310-rw", "https://lh3.googleusercontent.com/3GpwxSYBi9ZddmNBQESyFpPKNkuUaDPy6UmyxCYnF0dGlbwVlwPPO-elyE74n8dxpQ=w720-h310-rw", "https://lh3.googleusercontent.com/Y26WfpWu6clcMfJ5R75ZmQmyK3iWjUL8beos0_j1Ae0yz3r1lpKfYSsWn8f4dNHb6UU=w720-h310-rw", "https://lh3.googleusercontent.com/1ENCeqKrg5KTf3SyqG3LXaBwiqRrczXav8kqDiIMBtelispNhRscv09WDXKdA6mPMVOk=w720-h310-rw", "https://lh3.googleusercontent.com/ZrsDsdFl-Wbi-TmXd14AqdkzHPOWL2atYlZ_-ZACSy3kw1iYMsjgqVZC6EartuDzNh4=w720-h310-rw", "https://lh3.googleusercontent.com/TmrLEcb8UY0Jwe8ueS4haYnMhvCJInxoZ2UG5ezyq-bHowdSdIDr8mUoJ2nPQRWjKBmb=w720-h310-rw", "https://lh3.googleusercontent.com/Bt1YXZGG8Udb03twG9wyNIEawQd5K7XUveoS4mrCnOMePXbdxhEVWhfzd8rFZ3rd7dU=w720-h310-rw", "https://lh3.googleusercontent.com/Rr5ZqnG2DzBzdIqB6IJjYQw7sUL4iceYpIAlxkqK0eh2mJsPn6IU4B_midJ1ViFbAB27=w720-h310-rw", "https://lh3.googleusercontent.com/UNxhgAxOHqj97IVUo-y_bPoAlhmmU1h5g9BTgxDZWVmewksGkjB6lxgbyrhBIdiAhA=w720-h310-rw", "https://lh3.googleusercontent.com/AU01uNwNjGft5u8oPQLRtUbrEe84E-yU_wCRiK_a6a7sfoVOnHsBbT9Y4ksEdgtlbq0=w720-h310-rw"], "video": null, "category": ["FINANCE"], "score": "4.7", "histogram": {"5": null, "4": null, "3": null, "2": null, "1": null}, "reviews": 12638, "description": "A Username and Password is required for logging into this app and can only be created when registering for online banking.  To register for Delta Community\u2019s Online Banking service, visit our website at www.DeltaCommunityCU.com and choose New Enrollment in the login box.\nEnjoy the convenience of managing your account anywhere and at any time. You can check your balance, transfer funds, make a bill payment and now add money to your account with our newest Mobile Deposit feature. It\u2019s like having a tiny branch in the palm of your hands. Download and get started today!\nFEATURES OF Delta Community Credit Union MOBILE BANKING\n\u2022\tReview account balances and transactions\n\u2022\tTransfer funds between accounts\n\u2022\tPay bills**\n\u2022\tView copies of cleared checks\n\u2022\tLocate surcharge-free ATM\u2019s and Delta Community Credit Union branches\nSAFE AND SECURE\nDelta Community Credit Union uses SSL (Secure Socket Layer) encryption to communicate securely through all mobile devices.\n*Must be enrolled in Online Banking. There is no charge from Delta Community Credit Union, but messaging and data rates may apply.\n**Must have Bill Pay setup previously in Online Banking.", "description_html": "A Username and Password is required for logging into this app and can only be created when registering for online banking.  To register for Delta Community\u2019s Online Banking service, visit our website at www.DeltaCommunityCU.com and choose New Enrollment in the login box.<br/><br/>Enjoy the convenience of managing your account anywhere and at any time. You can check your balance, transfer funds, make a bill payment and now add money to your account with our newest Mobile Deposit feature. It\u2019s like having a tiny branch in the palm of your hands. Download and get started today!<br/><br/>FEATURES OF Delta Community Credit Union MOBILE BANKING<br/>\u2022\tReview account balances and transactions<br/>\u2022\tTransfer funds between accounts<br/>\u2022\tPay bills**<br/>\u2022\tView copies of cleared checks<br/>\u2022\tLocate surcharge-free ATM\u2019s and Delta Community Credit Union branches <br/><br/>SAFE AND SECURE<br/>Delta Community Credit Union uses SSL (Secure Socket Layer) encryption to communicate securely through all mobile devices.<br/><br/>*Must be enrolled in Online Banking. There is no charge from Delta Community Credit Union, but messaging and data rates may apply.<br/>**Must have Bill Pay setup previously in Online Banking.", "recent_changes": null, "editors_choice": false, "price": "0", "free": true, "iap": false, "developer_id": "DELTA+COMMUNITY+CREDIT+UNION", "updated": "July 30, 2020", "size": "22M", "installs": "100,000+", "current_version": "6.4.1.0", "required_android_version": "7.0 and up", "content_rating": ["Everyone"], "iap_range": null, "interactive_elements": null, "developer": "DELTA COMMUNITY CREDIT UNION", "developer_email": "onlinebanking@deltacommunitycu.com", "developer_url": "http://www.deltacommunitycu.com", "developer_address": null, "app_id": "com.ifs.banking.fiid1484", "url": "https://play.google.com/store/apps/details?id=com.ifs.banking.fiid1484"}