{"title": "Transit  \u2022 Bus & Subway Times", "icon": "https://lh3.googleusercontent.com/rDVnZ9rwreErP5_wwGrSVtx-prgRBTCJwdCP9iQFkt_3EerJzB0rxA15EIAGYXUNZA", "screenshots": ["https://lh3.googleusercontent.com/v8Pvx9gkpOLKrokT4jycQJ-_Z52wQJdUNHdO82I0YsRLAdk8zYZqzM9YpWDaDXdSLXI=w720-h310-rw", "https://lh3.googleusercontent.com/BETJWPh6Pk5eBtFDK2geSRX19MbMZvs4P2IJ3fdCnwLZyFs0kCVqaOCZyeSWm6-R48TK=w720-h310-rw", "https://lh3.googleusercontent.com/K4kI_bm-uFDE35I0jPcjH10oR0hrjnGLcNMf0crZU941SqbD2uYTVTisYzkvOBOIWJo=w720-h310-rw", "https://lh3.googleusercontent.com/ytVV5WpvzywsiJK9HTKVnDHgSXElspbDeHG2eDn83CcvcIW2uquxLzIX9o8U90hqZBtq=w720-h310-rw", "https://lh3.googleusercontent.com/PdpxB8HzxQZjbsHyATXrtcyHaCr1Fn60qeWqBocRfku1ENzWZf6dRP1fus8glolMroU=w720-h310-rw", "https://lh3.googleusercontent.com/WQWs0LYV6kI7xPoyI3TGUvxckjmNFgLc295YH62Fh__4e_NCOwWxBTmQg2T9RCxha_c=w720-h310-rw", "https://lh3.googleusercontent.com/oAvsleym-m0jL9ZYpfoiuhKRSX7MJbAKqhB_pl5L-AwcmttjgcGoagBeNDCMLNRX_9PJ=w720-h310-rw", "https://lh3.googleusercontent.com/kND_tJutIaIOnDBfXmEaaRTg8crK6nLHk3IYgZXsdZ0i9NCe7mqPtOdlE7qkVqkmySk=w720-h310-rw"], "video": null, "category": ["MAPS_AND_NAVIGATION"], "score": "4.3", "histogram": {"5": null, "4": null, "3": null, "2": null, "1": null}, "reviews": 64250, "description": "Transit is your real-time city travel companion. It works in 200+ cities, for buses, trains, Ubers, Lyfts, and everything in between. Get precise real-time predictions for public transit, the smartest & fastest trip plans, and a step-by-step navigator when you\u2019re going to unfamiliar destinations (or to wake you up from a mid-trip nap\u2122). Our app gives you all the info you need, in a clear, bold interface so you don\u2019t get lost or stuck at the stop.\nWhether you\u2019re new to a city\u2026 or a subway expert who takes NYC\u2019s MTA / LA Metro / WMATA / MBTA / BART / CTA / SEPTA every day (or the 200+ other systems  we support) this is the award-winning app you need \ud83d\ude4c\n*Turn on mobile data to get real-time information\n**No data? Don\u2019t worry: our trip planner works offline, using the bus / train schedule.\n\ud83c\udf1f Google Play Picks\n\ud83d\uddfdNYC MTA App Quest award winner\n\ud83d\udcf0 \u201cKiller App\u201d \u2014 WSJ\u2019s NYC subway reporter\n\ud83c\udfc6 \"MBTA has a favorite transit app, and it's called Transit\" \u2014 Boston Globe\n\u23f0 \u201cYou won't realize how much time you can save until you use this app\u201d \u2014 LA Times\n\ud83d\udcaa \u201cThe best app for CTA buses\u201d \u2014 Reddit Chicago\n\ud83d\udd25 And trusted by the New York Times\u2019 own tech critic, Mike Isaac\n\ud83d\udd0d What features does this app support?\n- Real-time map that shows you where your ride is \ud83d\udccd\n- Subway maps \ud83d\uddfa\ufe0f\n- Trip planner (works offline)\n- Explore different combinations of trips to find the fastest, cheapest way to your destination (i.e. how does a train trip compare to a \u201cbus + bikeshare\u201d trip? Or a \u201ctrain + Uber\u201d trip?)\n- Real-time predictions, telling you when your train, subway, bus, ferry, metro, etc. will show up\n- Step-by-step navigator (including transfers)\n- Voice reminders to start walking to your stop, to hurry up (if your bus or subway is arriving early) and where to get off\n- Schedules, route itineraries, connecting lines at every stop\n- Pay for bus & train tickets, bikeshare passes & ridehail fares in the app (select cities)\n- Bike directions\n- Compare ETAs & prices for Uber, Lyft and Via\n- See ALL nearby bikeshares, scooters, and carshares\n- Support for everything: bus / metro / subway / light rail / streetcar / train / ridehail / bikeshare / scooters / carshare / ferry\n\ud83d\ude4b Where does this app work?\n200+ supported cities, including NYC, Chicago, Washington DC, LA, SF & the Bay Area, Toronto, Montreal, Vancouver, Paris, and many more cities across North America, Europe, Australia and NZ\n\u26be Full list of US cities \u26be (including bus, train, subway, and ferry systems)\nAtlanta: MARTA, CCT, GRTA\nAustin: Capital Metro\nBaltimore: MTA\nBoston: MBTA, Hubway\nBuffalo: NFTA, Fort Erie Transit\nCharlotte: CATS\nChicago: CTA, Metra, PACE, NICTD, Divvy\nCincinnati: Metro, TANK\nCleveland: RTA\nColumbus: COTA, CoGo\nDallas: DART, Fort Worth T\nDenver: RTD\nHampton Roads: HRT\nHartford (and CT): CTTransit, CTFastrak\nHonolulu: TheBus\nHouston: METRO\nLas Vegas: RTC\nLos Angeles: LA Metro, Metrolink, OCTA, LADOT, Omnitrans, RTA, Burbank Bus, Foothill, Big Blue Bus, Glendale Beeline\nLouisville: TARC\nMadison: Metro\nMiami: MDT, BCT, Palm Tran, Tri-Rail, Citibike\nMilwaukee: MCTS\nMinneapolis: Metro Transit, MVTA, Plymouth, SouthWest, U. Minnesota, Nice Ride\nNew Orleans: RTA\nNYC Metro: New York MTA, Metro-North (MNR), Long Island Rail Road (LIRR), NJ Transit (NJT), PATH, SI Ferry, NICE, Bee-Line, RI Tram, NY Waterway, SIR, CitiBike\nOrlando: Lynx\nPhiladelphia: SEPTA, PATCO, Indego\nPhoenix: Valley Metro\nPittsburgh: Port Authority (PAAC)\nPortland: TriMet\nSLC: UTA, GREENbike\nSacramento: Capitol Corridor, SRT\nSan Antonio: VIA Metropolitan\nSan Diego: MTS, NCTD\nSF Bay Area: SF BART, SFMTA (SF MUNI), Caltrain, AC Transit, VTA, County Connection, SamTrans, Bay Wheels\nSeattle: Metro Transit, City of Seattle, Sound Transit, Pierce Transit, Pronto\nSt. Louis: Metro\nTampa Bay: HART, PSTA\nWashington DC: WMATA (DC Metro & Bus), DC Circulator, Ride On, Arlington (ART), Fairfax Connector, VRE, DASH, Capital Bike Share\n+100s more cities, including Paris, Montreal, Toronto, Vancouver, London, and more!", "description_html": "Transit is your real-time city travel companion. It works in 200+ cities, for buses, trains, Ubers, Lyfts, and everything in between. Get precise real-time predictions for public transit, the smartest &amp; fastest trip plans, and a step-by-step navigator when you\u2019re going to unfamiliar destinations (or to wake you up from a mid-trip nap\u2122). Our app gives you all the info you need, in a clear, bold interface so you don\u2019t get lost or stuck at the stop.<br/><br/>Whether you\u2019re new to a city\u2026 or a subway expert who takes NYC\u2019s MTA / LA Metro / WMATA / MBTA / BART / CTA / SEPTA every day (or the 200+ other systems  we support) this is the award-winning app you need \ud83d\ude4c<br/><br/>*Turn on mobile data to get real-time information<br/>**No data? Don\u2019t worry: our trip planner works offline, using the bus / train schedule.<br/><br/>\ud83c\udf1f Google Play Picks<br/>\ud83d\uddfdNYC MTA App Quest award winner<br/>\ud83d\udcf0 \u201cKiller App\u201d \u2014 WSJ\u2019s NYC subway reporter<br/>\ud83c\udfc6 \"MBTA has a favorite transit app, and it's called Transit\" \u2014 Boston Globe<br/>\u23f0 \u201cYou won't realize how much time you can save until you use this app\u201d \u2014 LA Times<br/>\ud83d\udcaa \u201cThe best app for CTA buses\u201d \u2014 Reddit Chicago<br/>\ud83d\udd25 And trusted by the New York Times\u2019 own tech critic, Mike Isaac<br/><br/>\ud83d\udd0d What features does this app support?<br/>- Real-time map that shows you where your ride is \ud83d\udccd<br/>- Subway maps \ud83d\uddfa\ufe0f<br/>- Trip planner (works offline)<br/>- Explore different combinations of trips to find the fastest, cheapest way to your destination (i.e. how does a train trip compare to a \u201cbus + bikeshare\u201d trip? Or a \u201ctrain + Uber\u201d trip?)<br/><br/><br/>- Real-time predictions, telling you when your train, subway, bus, ferry, metro, etc. will show up<br/>- Step-by-step navigator (including transfers)<br/>- Voice reminders to start walking to your stop, to hurry up (if your bus or subway is arriving early) and where to get off<br/>- Schedules, route itineraries, connecting lines at every stop<br/>- Pay for bus &amp; train tickets, bikeshare passes &amp; ridehail fares in the app (select cities)<br/><br/>- Bike directions<br/>- Compare ETAs &amp; prices for Uber, Lyft and Via<br/>- See ALL nearby bikeshares, scooters, and carshares<br/>- Support for everything: bus / metro / subway / light rail / streetcar / train / ridehail / bikeshare / scooters / carshare / ferry<br/><br/>\ud83d\ude4b Where does this app work?<br/>200+ supported cities, including NYC, Chicago, Washington DC, LA, SF &amp; the Bay Area, Toronto, Montreal, Vancouver, Paris, and many more cities across North America, Europe, Australia and NZ<br/><br/>\u26be Full list of US cities \u26be (including bus, train, subway, and ferry systems)<br/><br/>Atlanta: MARTA, CCT, GRTA<br/>Austin: Capital Metro<br/>Baltimore: MTA<br/>Boston: MBTA, Hubway<br/>Buffalo: NFTA, Fort Erie Transit<br/>Charlotte: CATS<br/>Chicago: CTA, Metra, PACE, NICTD, Divvy<br/>Cincinnati: Metro, TANK<br/>Cleveland: RTA <br/>Columbus: COTA, CoGo<br/>Dallas: DART, Fort Worth T<br/>Denver: RTD<br/>Hampton Roads: HRT<br/>Hartford (and CT): CTTransit, CTFastrak<br/>Honolulu: TheBus<br/>Houston: METRO<br/>Las Vegas: RTC<br/>Los Angeles: LA Metro, Metrolink, OCTA, LADOT, Omnitrans, RTA, Burbank Bus, Foothill, Big Blue Bus, Glendale Beeline<br/>Louisville: TARC<br/>Madison: Metro<br/>Miami: MDT, BCT, Palm Tran, Tri-Rail, Citibike<br/>Milwaukee: MCTS<br/>Minneapolis: Metro Transit, MVTA, Plymouth, SouthWest, U. Minnesota, Nice Ride<br/>New Orleans: RTA<br/>NYC Metro: New York MTA, Metro-North (MNR), Long Island Rail Road (LIRR), NJ Transit (NJT), PATH, SI Ferry, NICE, Bee-Line, RI Tram, NY Waterway, SIR, CitiBike<br/>Orlando: Lynx<br/>Philadelphia: SEPTA, PATCO, Indego<br/>Phoenix: Valley Metro<br/>Pittsburgh: Port Authority (PAAC)<br/>Portland: TriMet<br/>SLC: UTA, GREENbike<br/>Sacramento: Capitol Corridor, SRT<br/>San Antonio: VIA Metropolitan<br/>San Diego: MTS, NCTD<br/>SF Bay Area: SF BART, SFMTA (SF MUNI), Caltrain, AC Transit, VTA, County Connection, SamTrans, Bay Wheels<br/>Seattle: Metro Transit, City of Seattle, Sound Transit, Pierce Transit, Pronto<br/>St. Louis: Metro<br/>Tampa Bay: HART, PSTA<br/>Washington DC: WMATA (DC Metro &amp; Bus), DC Circulator, Ride On, Arlington (ART), Fairfax Connector, VRE, DASH, Capital Bike Share<br/>+100s more cities, including Paris, Montreal, Toronto, Vancouver, London, and more!", "recent_changes": null, "editors_choice": false, "price": "0", "free": true, "iap": false, "developer_id": "5688185120427149899", "updated": "August 4, 2020", "size": "Varies with device", "installs": "5,000,000+", "current_version": "5.7.16", "required_android_version": "Varies with device", "content_rating": ["Everyone"], "iap_range": null, "interactive_elements": null, "developer": "Transit App, Inc.", "developer_email": "info@transit.app", "developer_url": "https://transit.app?utm_source=googleplay&utm_medium=store", "developer_address": null, "app_id": "com.thetransitapp.droid", "url": "https://play.google.com/store/apps/details?id=com.thetransitapp.droid"}