{"title": "Microsoft Bing Search", "icon": "https://lh3.googleusercontent.com/0aRIOVqPu3KKUh6FFSmo1jkQMIeTqgGvHNo4mHl_NUzJxGGd2m0jaUoRdhGcgaa-ug", "screenshots": ["https://lh3.googleusercontent.com/dpZIdEhoFeoIGm1QVkBFta9Ku4pXE6yhMc8-BhgNDi_-RRjsPUWD6t9D1K3NjUHlvyoG=w720-h310-rw", "https://lh3.googleusercontent.com/USr0HW49gYVJ4JeD2JOLSE1_wUCg2LZ4d0XE4VKvP0Fk6V0NM198sr9ISIUeWIuZmHE=w720-h310-rw", "https://lh3.googleusercontent.com/kqRvMj8n4QP0_MXN7qjhi_29mwJ2vzcgTOmoekeNWxHEreCqQwILTjJI03VYrDmeAcHG=w720-h310-rw", "https://lh3.googleusercontent.com/BUkyduw6r6thDl5OJxC5blcfEfostwtS1dK2ZSCyIMDGgsKxj_VgdAmN1e3X5kcFuYOk=w720-h310-rw", "https://lh3.googleusercontent.com/CGLosWVnEWX5jeurtl_JIGpOVyUQGX_6X3s3D-mqllQUrNfIkRFt5IyUcH3dFv6Gvoo=w720-h310-rw", "https://lh3.googleusercontent.com/1vE-WRuSOYbzBwerV_rN4SLjchSeocx4FUMvUrUItO1nV-AHjXm5dygNlMjIXZbDolQ=w720-h310-rw", "https://lh3.googleusercontent.com/FPI47TiGqP-lN-kLlKRJgV6eIDW_rsBp0RtWaymbmqmprcXKrJ7wlzJJlss_LlTx0A=w720-h310-rw", "https://lh3.googleusercontent.com/xGZGeaBFTgxsl7--H94rG6CqD2OoeYcZrtFBlpAxiCMuzpJ33fivbTZBx-wtqSMDgg=w720-h310-rw", "https://lh3.googleusercontent.com/EJhHTnsDawUqunXzPzwTtzgeoh4y9b_sIJ9MjhyJoY84RWP1bs2Rq-Yvo6p9h9JsFUrD=w720-h310-rw", "https://lh3.googleusercontent.com/0_qh3cHk6VkX84VE4U5q5286wh6cfmKM2Tz_yyAESsaIOeiOi3arVxOPTsCorzVGzQ=w720-h310-rw", "https://lh3.googleusercontent.com/U13khXr7iNb7GDIOzNJ5JLunkPaj3IPrsGtLfxS3T9D1OwZu_aHI0yde-5_Mifv-9xE=w720-h310-rw", "https://lh3.googleusercontent.com/em5mzpQOUup_eNB5QxfxT1VaWf7I1CVLihXCnFWKgf2s5047FYOnV1mZBBmZGZlxusk=w720-h310-rw", "https://lh3.googleusercontent.com/N1NJcjBAgPNnSfFkIXvkNKRU3-PHe90QTCRRHpp3sxohoORdOzvo3w4pCms3CQBzqA=w720-h310-rw", "https://lh3.googleusercontent.com/3guwmCre29yZpDxibWlCqgL4SyP9nZDPisgznLm6NwXoYZ0zF5qtY-KOdn1WmLJN0SA=w720-h310-rw", "https://lh3.googleusercontent.com/T7prdvIY_RcwOInc1ejdeE9AFU-VReZGqdP1jUmGNItGOjcakUItTmy3AiCs9xnD5Q=w720-h310-rw", "https://lh3.googleusercontent.com/6N4vXdyF6JSxQ15r58lpWnLhxTlPyvn-8u2JdI_6BpKZ_5JK1HSlPv8iLySD6q_W8Ng=w720-h310-rw", "https://lh3.googleusercontent.com/kibjEqYnmUwi95BenljN6SJaEH0aTfS0nVbTJg2E0ebzrTIPAGEHhvbFlFAJbA-vBIge=w720-h310-rw", "https://lh3.googleusercontent.com/2tln7HuPEWWoYwX5QtlYonTilpUjPttAvRBdH3KPYgUJgTqPxbY6yeNDHjJ_tNtc7HA=w720-h310-rw", "https://lh3.googleusercontent.com/kf2EVkzKpfBvvDncNIyVWfeZpfezwC2fPnBLTOrj9rw7wyISIAiMSDOyM5UgnNtzYZw=w720-h310-rw", "https://lh3.googleusercontent.com/tpLVk7akBnlB9IZZNicfzAtnCkaNP5rF8ocHVtD-v9CO9wlA-e1BX9X1YvPMPgiDzQg=w720-h310-rw"], "video": null, "category": ["TOOLS"], "score": "4.5", "histogram": {"5": null, "4": null, "3": null, "2": null, "1": null}, "reviews": 164369, "description": "Bing is more than just search.\nBing is the only search engine that rewards you for your curiosity. Get points when you search and redeem them for gift cards at Amazon, Starbucks, and more!\nWallpaper\n: See beautiful wallpapers from around the world, only in Bing.\nRewards\n: Get points when you search, and redeem them for gift cards at Amazon, Starbucks, and much more!\nYour feed\n: Swipe up on the home page to catch up with what's happening in the world and get personalized updates on your feed.\nReading mode\n: Switch on reading mode to focus on the text, distraction-free.\nSave money\n: Use the built-in barcode scanner to review products and compare prices.\nEntertainment & Nearby\n: Find what you love, from live sport updates, trending music, and recipes, to nearby deals, movie times, and gas prices.\nIntelligent camera search\n: Learn more about the world around you. Whether it's animals, landmarks, or even fashion, searching is as simple as snapping a picture.\nVoice search\n: What's the best way to get an answer? Ask a question. Talk to Bing and get instant results.\nFast search\n: Get to know the world with one click. Answer your questions faster and easier.\nSecure Browsing\n: Protect your privacy. Private mode lets you browse without saving your history, cache, cookies, and personalization info.\n* Some features are not available in all countries.", "description_html": "Bing is more than just search.<b> Bing is the only search engine that rewards you for your curiosity. Get points when you search and redeem them for gift cards at Amazon, Starbucks, and more!</b><br/><br/><b>Wallpaper</b>: See beautiful wallpapers from around the world, only in Bing.<br/><b>Rewards</b>: Get points when you search, and redeem them for gift cards at Amazon, Starbucks, and much more!<br/><b>Your feed</b>: Swipe up on the home page to catch up with what's happening in the world and get personalized updates on your feed.<br/><b>Reading mode</b>: Switch on reading mode to focus on the text, distraction-free.<br/><b>Save money</b>: Use the built-in barcode scanner to review products and compare prices. <br/><b>Entertainment &amp; Nearby</b>: Find what you love, from live sport updates, trending music, and recipes, to nearby deals, movie times, and gas prices.<br/><b>Intelligent camera search</b>: Learn more about the world around you. Whether it's animals, landmarks, or even fashion, searching is as simple as snapping a picture.<br/><b>Voice search</b>: What's the best way to get an answer? Ask a question. Talk to Bing and get instant results.<br/><b>Fast search</b>: Get to know the world with one click. Answer your questions faster and easier. <br/><b>Secure Browsing</b>: Protect your privacy. Private mode lets you browse without saving your history, cache, cookies, and personalization info.<br/><i>* Some features are not available in all countries.</i>", "recent_changes": null, "editors_choice": false, "price": "0", "free": true, "iap": false, "developer_id": "6720847872553662727", "updated": "July 30, 2020", "size": "Varies with device", "installs": "10,000,000+", "current_version": "Varies with device", "required_android_version": "5.0 and up", "content_rating": ["Everyone"], "iap_range": null, "interactive_elements": ["Unrestricted Internet"], "developer": "Microsoft Corporation", "developer_email": "bfafeedback@microsoft.com", "developer_url": "https://www.bing.com", "developer_address": "One Microsoft Way", "app_id": "com.microsoft.bing", "url": "https://play.google.com/store/apps/details?id=com.microsoft.bing"}