{"title": "Guidebook", "icon": "https://lh3.googleusercontent.com/1u-DmCP64uQ-nluP9YH539RB48-a2BKfZi4k4gT4pzE-d3H8eIXLvFo6---m-LVFfA", "screenshots": ["https://lh3.googleusercontent.com/9Ck8LiY9QS--CpWqCJZj1muVAd763gVg4Uon4tywlpwyAWQa8khj5hNCwfE_dNyTS4c=w720-h310-rw", "https://lh3.googleusercontent.com/T2XnH6U52HHQvKMB17A9MBytrdCw6W0Q4JY2iNExHoS9ey84gN1PZ2CoIXHNIR5QQ1TN=w720-h310-rw", "https://lh3.googleusercontent.com/4-bFzDVlWtmAFsRSTgX-vMcEbL6ui5rmxEnLUFxOaM6-St11kVpc_4-CDdjQk3xEJok=w720-h310-rw"], "video": null, "category": ["TRAVEL_AND_LOCAL"], "score": "4.7", "histogram": {"5": null, "4": null, "3": null, "2": null, "1": null}, "reviews": 3697, "description": "Guidebook is your guide to events, conferences, campuses, and more. Download the app to:\n[+] Build your personal schedule and to-do lists.\n[+] Easily access speaker, sponsor, exhibitor information, and more.\n[+] View maps of the venue and local area.\n[+] Simply search for information within the app.\n[+] Connect and engage with other attendees through private messages.\n[+] Share photos, likes, and comments on the interactive social feed.\nWant to build your own app? Visit guidebook.com to start building your first mobile app today.", "description_html": "Guidebook is your guide to events, conferences, campuses, and more. Download the app to:<br/><br/>[+] Build your personal schedule and to-do lists.<br/>[+] Easily access speaker, sponsor, exhibitor information, and more.<br/>[+] View maps of the venue and local area.<br/>[+] Simply search for information within the app.<br/>[+] Connect and engage with other attendees through private messages.<br/>[+] Share photos, likes, and comments on the interactive social feed.<br/><br/>Want to build your own app? Visit guidebook.com to start building your first mobile app today.", "recent_changes": null, "editors_choice": false, "price": "0", "free": true, "iap": false, "developer_id": "Guidebook+Inc", "updated": "July 27, 2020", "size": "27M", "installs": "1,000,000+", "current_version": "7.16.1", "required_android_version": "5.0 and up", "content_rating": ["Everyone"], "iap_range": null, "interactive_elements": ["Users Interact"], "developer": "Guidebook Inc", "developer_email": "support@guidebook.com", "developer_url": "http://guidebook.com", "developer_address": "Guidebook, Inc\n340 Bryant St, STE 400\nSan Francisco, CA 94107", "app_id": "com.guidebook.android", "url": "https://play.google.com/store/apps/details?id=com.guidebook.android"}